LICENSE.txt
MANIFEST.in
README.md
local-requirements.txt
pyproject.toml
setup.cfg
setup.py
tox.ini
versioneer.py
src/scikits/odes/__init__.py
src/scikits/odes/dae.py
src/scikits/odes/ddaspk.py
src/scikits/odes/ddaspkint.py
src/scikits/odes/dopri5.py
src/scikits/odes/lsodi.py
src/scikits/odes/lsodiint.py
src/scikits/odes/ode.py
src/scikits/odes/odeint.py
src/scikits/odes/sundials/__init__.py
src/scikits/odes/sundials/common_defs.py
src/scikits/odes/sundials/cvode.py
src/scikits/odes/sundials/cvodes.py
src/scikits/odes/sundials/ida.py
src/scikits/odes/sundials/idas.py
src/scikits/odes/tests/__init__.py
src/scikits/odes/tests/test_dae.py
src/scikits/odes/tests/test_dop.py
src/scikits/odes/tests/test_get_info.py
src/scikits/odes/tests/test_odeint.py
src/scikits/odes/tests/test_on_funcs_cvode.py
src/scikits/odes/tests/test_on_funcs_ida.py
src/scikits/odes/tests/test_user_return_vals_cvode.py
src/scikits/odes/tests/test_user_return_vals_ida.py
src/scikits_odes/__init__.py
src/scikits_odes/_version.py
src/scikits_odes/dae.py
src/scikits_odes/dopri5.py
src/scikits_odes/ode.py
src/scikits_odes/odeint.py
src/scikits_odes.egg-info/PKG-INFO
src/scikits_odes.egg-info/SOURCES.txt
src/scikits_odes.egg-info/dependency_links.txt
src/scikits_odes.egg-info/requires.txt
src/scikits_odes.egg-info/top_level.txt